setup.py
jw/__init__.py
jw.badipsrbl.egg-info/PKG-INFO
jw.badipsrbl.egg-info/SOURCES.txt
jw.badipsrbl.egg-info/dependency_links.txt
jw.badipsrbl.egg-info/entry_points.txt
jw.badipsrbl.egg-info/requires.txt
jw.badipsrbl.egg-info/top_level.txt
jw/badips/__init__.py
jw/badips/main.py
test/test10_request.py