Metadata-Version: 1.1
Name: jw.badipsrbl
Version: 0.1.21
Summary: RBL DNS Server for badips.com
Home-page: https://pypi.python.org/pypi/jw.badipsrbl
Author: Johnny Wezel
Author-email: dev-jay@wezel.name
License: GPL 3
Keywords: rbl dns badips
Platform: POSIX
Classifier: Development Status :: 3 - Alpha
Classifier: Environment :: No Input/Output (Daemon)
Classifier: Intended Audience :: Developers
Classifier: License :: OSI Approved :: GNU General Public License v3 or later (GPLv3+)
Classifier: Natural Language :: English
Classifier: Operating System :: POSIX
Classifier: Operating System :: Unix
Classifier: Programming Language :: Python :: 2
Classifier: Programming Language :: Python :: 2.7
